Metadata-Version: 2.1
Name: lineaug
Version: 0.1
Summary: Augment line images for improving OCR datasets 
Home-page: https://github.com/maxnth/lineaug
Author: Maximilian Nöth
Author-email: maximilian.noeth@protonmail.com
License: MIT License
Keywords: Augmentation,OCR,optical character recognition
Platform: UNKNOWN
Classifier: Programming Language :: Python :: 3
Classifier: License :: OSI Approved :: MIT License
Classifier: Operating System :: OS Independent
Requires-Python: >=3.6
